MANIFEST.in
README.rst
bootstrap-buildout.py
setup.py
version.txt
bob/__init__.py
bob.db.multispectral_spoof.egg-info/PKG-INFO
bob.db.multispectral_spoof.egg-info/SOURCES.txt
bob.db.multispectral_spoof.egg-info/dependency_links.txt
bob.db.multispectral_spoof.egg-info/entry_points.txt
bob.db.multispectral_spoof.egg-info/namespace_packages.txt
bob.db.multispectral_spoof.egg-info/not-zip-safe
bob.db.multispectral_spoof.egg-info/requires.txt
bob.db.multispectral_spoof.egg-info/top_level.txt
bob/db/__init__.py
bob/db/multispectral_spoof/__init__.py
bob/db/multispectral_spoof/driver.py
bob/db/multispectral_spoof/models.py
bob/db/multispectral_spoof/spoofing.py
bob/db/multispectral_spoof/test.py
bob/db/multispectral_spoof/listfiles/attack.txt
bob/db/multispectral_spoof/listfiles/enroll.txt
bob/db/multispectral_spoof/listfiles/real.txt