Metadata-Version: 1.1
Name: bob.db.multispectral-spoof
Version: 1.0.1
Summary: Mutlispectral (VIS + NIR) Face Spoofing Database Access API for Bob
Home-page: http://pypi.python.org/pypi/bob.db.multispectral_spoof
Author: Ivana Chingovska
Author-email: ivana.chingovska@idiap.ch
License: GPLv3
Platform: UNKNOWN
Classifier: Development Status :: 4 - Beta
Classifier: Intended Audience :: Science/Research
Classifier: License :: OSI Approved :: GNU General Public License v3 (GPLv3)
Classifier: Natural Language :: English
Classifier: Programming Language :: Python
Classifier: Programming Language :: Python :: 3
Classifier: Topic :: Scientific/Engineering :: Artificial Intelligence
Classifier: Topic :: Database :: Front-Ends
